[
 {
  "id": 1,
  "usuario": "nicolasmarco841",
  "password": "$2a$10$gfM79IrlDN9nQMN/kbxBbunntY2MTM92zJVnGRQ2MWAzpqp6sB8gK",
  "nombre": "Nicolás Agustín",
  "apellido": "Marco",
  "email": "Nicolasmarco841@gmail.com",
  "telefono": "1156610726",
  "imagen": "default.png",
  "administrador": true
 },
 {
  "id": 2,
  "usuario": "simonprince",
  "password": "$2a$10$qGNjIxWGIZjlamW1GzYISuFmn.NPm1MWVqfH7PGmKrGVDxE7/5eCi",
  "nombre": "Simon",
  "apellido": "Prince",
  "email": "simon00prince@gmail.com",
  "telefono": "1173737829",
  "imagen": "default.png",
  "administrador": true
 }
]